dnd5epy/__init__.py
dnd5epy/api/__init__.py
dnd5epy/api/character_data_api.py
dnd5epy/api/class_api.py
dnd5epy/api/class_levels_api.py
dnd5epy/api/class_resource_lists_api.py
dnd5epy/api/common_api.py
dnd5epy/api/equipment_api.py
dnd5epy/api/feats_api.py
dnd5epy/api/features_api.py
dnd5epy/api/game_mechanics_api.py
dnd5epy/api/monsters_api.py
dnd5epy/api/races_api.py
dnd5epy/api/rules_api.py
dnd5epy/api/spells_api.py
dnd5epy/api/subclasses_api.py
dnd5epy/api/subraces_api.py
dnd5epy/api/traits_api.py
dnd5epy/api_client.py
dnd5epy/api_response.py
dnd5epy/configuration.py
dnd5epy/exceptions.py
dnd5epy/models/__init__.py
dnd5epy/models/ability_bonus.py
dnd5epy/models/ability_score.py
dnd5epy/models/alignment.py
dnd5epy/models/api_reference.py
dnd5epy/models/api_reference_list.py
dnd5epy/models/area_of_effect.py
dnd5epy/models/armor.py
dnd5epy/models/background.py
dnd5epy/models/background_all_of_feature.py
dnd5epy/models/choice.py
dnd5epy/models/class_all_of_starting_equipment.py
dnd5epy/models/class_level.py
dnd5epy/models/class_level_class_specific.py
dnd5epy/models/class_level_class_specific_any_of.py
dnd5epy/models/class_level_class_specific_any_of1.py
dnd5epy/models/class_level_class_specific_any_of10.py
dnd5epy/models/class_level_class_specific_any_of11.py
dnd5epy/models/class_level_class_specific_any_of2.py
dnd5epy/models/class_level_class_specific_any_of3.py
dnd5epy/models/class_level_class_specific_any_of4.py
dnd5epy/models/class_level_class_specific_any_of5.py
dnd5epy/models/class_level_class_specific_any_of5_martial_arts.py
dnd5epy/models/class_level_class_specific_any_of6.py
dnd5epy/models/class_level_class_specific_any_of7.py
dnd5epy/models/class_level_class_specific_any_of8.py
dnd5epy/models/class_level_class_specific_any_of9.py
dnd5epy/models/class_level_class_specific_any_of9_creating_spell_slots_inner.py
dnd5epy/models/condition.py
dnd5epy/models/cost.py
dnd5epy/models/damage.py
dnd5epy/models/damage_at_character_level.py
dnd5epy-1.0.7.dist-info/METADATA
dnd5epy-1.0.7.dist-info/WHEEL
dnd5epy-1.0.7.dist-info/RECORD
