Metadata-Version: 2.1
Name: dnd5epy
Version: 1.0.7
Summary: D&D 5e API
Home-page: https://github.com/GIT_USER_ID/GIT_REPO_ID
License: MIT
Keywords: OpenAPI,OpenAPI-Generator,D&D 5e API
Author: 5eBits
Author-email: team@openapitools.org
Requires-Python: >=3.7,<4.0
Classifier: License :: OSI Approved :: MIT License
Classifier: Programming Language :: Python :: 3
Classifier: Programming Language :: Python :: 3.7
Classifier: Programming Language :: Python :: 3.8
Classifier: Programming Language :: Python :: 3.9
Classifier: Programming Language :: Python :: 3.10
Classifier: Programming Language :: Python :: 3.11
Requires-Dist: aenum (>=3.1.11)
Requires-Dist: pydantic (>=1.10.5,<2.0.0)
Requires-Dist: python-dateutil (>=2.8.2)
Requires-Dist: urllib3 (>=1.25.3)
Project-URL: Repository, https://github.com/GIT_USER_ID/GIT_REPO_ID
